<Properties GitUserInfo="UsingGIT" StartupConfiguration="{D09FBFBF-0A0B-42A1-8D1F-55410209C58F}|Default">
  <MonoDevelop.Ide.Workbench ActiveDocument="ExpenseManagement/wwwroot/css/site.css">
    <Files>
      <File FileName="ExpenseManagement/Areas/BankEmployees/Controllers/LoginAccountController.cs" Line="1" Column="1" />
      <File FileName="ExpenseManagement/Views/Shared/_Layout.cshtml" Line="34" Column="19" />
      <File FileName="ExpenseManagement/Views/Login/Index.cshtml" Line="25" Column="18" />
      <File FileName="ExpenseManagement/Startup.cs" Line="76" Column="45" />
      <File FileName="../../Documents/SBAdmin2/login.html" Line="9" Column="14" />
      <File FileName="ExpenseManagement/wwwroot/css/site.css" Line="1" Column="1" />
    </Files>
    <Pads>
      <Pad Id="ProjectPad">
        <State name="__root__">
          <Node name="ExpenseManagement" expanded="True">
            <Node name="ExpenseManagement" expanded="True">
              <Node name="Assets" expanded="True">
                <Node name="css" expanded="True" />
              </Node>
              <Node name="Controllers" expanded="True" />
              <Node name="Data" expanded="True" />
              <Node name="Models" expanded="True" />
              <Node name="Properties" expanded="True" />
              <Node name="Views" expanded="True">
                <Node name="Login" expanded="True" />
                <Node name="Shared" expanded="True" />
              </Node>
              <Node name="wwwroot" expanded="True">
                <Node name="css" expanded="True">
                  <Node name="site.css" selected="True" />
                </Node>
                <Node name="js" expanded="True" />
                <Node name="lib" expanded="True" />
              </Node>
              <Node name="appsettings.json" expanded="True" />
            </Node>
          </Node>
        </State>
      </Pad>
      <Pad Id="MonoDevelop.Debugger.WatchPad">
        <State />
      </Pad>
    </Pads>
  </MonoDevelop.Ide.Workbench>
  <MonoDevelop.Ide.DebuggingService.PinnedWatches />
  <MonoDevelop.Ide.ItemProperties.ExpenseManagement PreferredExecutionTarget="/Applications/Google Chrome.app" />
  <MonoDevelop.Ide.Workspace ActiveConfiguration="Debug" />
  <MonoDevelop.Ide.DebuggingService.Breakpoints>
    <BreakpointStore />
  </MonoDevelop.Ide.DebuggingService.Breakpoints>
  <MultiItemStartupConfigurations />
</Properties>